dual_flop_synchronizer.v
module dual_flop_synchronizer(
	input clk, in, rst,
	output reg out
);

reg sync_ff;

always @ (posedge clk or negedge rst) begin
	if (!rst) begin
		{out,sync_ff} <= 2'b00;
	end
	else begin
		out <= sync_ff;
		sync_ff <= in;
	end
end

endmodule

reciever_fsm.v
module reciever_fsm(
	input des_clk, req, rst,
	output reg des_ff_en, ack	
);

parameter idle = 2'b00, s1 = 2'b01, s2 = 2'b10;
reg [1:0] present_state, next_state;

always @ (posedge des_clk or negedge rst) begin
	if (!rst) begin
		present_state <= idle;
		{des_ff_en,ack} = 2'b00;
	end
	else present_state <= next_state;
end

always @ (*) begin
	case(present_state) 
		idle: begin
			next_state <= (req) ? s1 : idle;
			{des_ff_en,ack} <= 2'b00;
		end

		s1: begin
			next_state <= (req) ? s2 : idle;
			{des_ff_en,ack} <= 2'b11;
		end

		s2: begin
			next_state <= (req) ? s2 : idle;
			{des_ff_en,ack} <= 2'b01;
		end

		default: begin
			next_state <= idle;
			{des_ff_en,ack} <= 2'b00;
		end
	endcase
end

endmodule

sender_fsm.v
module sender_fsm(
	input src_clk, send, ack, rst,
	output reg req, busy, load_src_reg_en
);

parameter idle = 2'b00, s1 = 2'b01, s2 = 2'b10, s3 = 2'b11;
reg [1:0] present_state, next_state;

always @ (posedge src_clk or negedge rst) begin
	if (!rst) begin
		next_state <= idle;
		{req,busy,load_src_reg_en} <= 3'b000;		
	end
	
	else begin
		present_state <= next_state;		
	end
end	

always @ (present_state or send or ack) begin
	case(present_state)
		idle: begin
			{req,busy,load_src_reg_en} <= 3'b000;
			next_state <= (send) ? s1 : idle;
		end

		s1: begin
			{req,busy,load_src_reg_en} <= 3'b111;
			next_state <= (ack) ? s1 : s2;
		end

		s2: begin
			{req,busy,load_src_reg_en} <= 3'b110;
			next_state <= (ack) ? s3 : s2;
		end

		s3: begin
			{req,busy,load_src_reg_en} <= 3'b010;
			next_state <= (ack) ? s3 : idle;
		end

		default: begin
			{req,busy,load_src_reg_en} <= 3'b000;
			next_state <= idle;
		end
	endcase
end

endmodule

handshake_synchronizer.v
`include "dual_flop_synchronizer.v"
`include "sender_fsm.v"
`include "reciever_fsm.v"

module handshake_synchronizer #(parameter DATA_WIDTH = 8) (
	input src_clk, des_clk, rst, send, 
	input [DATA_WIDTH-1:0] data_src,
	output reg [DATA_WIDTH-1:0] data_des,
	output busy
);

wire req_src, ack_src, src_ff_en;
wire req_des, ack_des, des_ff_en;

sender_fsm sender_domain(
	.src_clk(src_clk), .send(send), .ack(ack_src), .rst(rst),
	.req(req_src), .busy(busy), .load_src_reg_en(src_ff_en)
);

reciever_fsm destination_domain(
	.des_clk(des_clk), .req(req_des), .rst(rst),
	.des_ff_en(des_ff_en), .ack(ack_des)
);

dual_flop_synchronizer src_to_des (
	.clk(des_clk), .in(req_src), .rst(rst),
	.out(req_des)
);

dual_flop_synchronizer des_to_src(
	.clk(src_clk), .in(ack_des), .rst(rst),
	.out(ack_src)
);

reg [DATA_WIDTH-1:0] src_ff, des_ff_in;

// Capture Flip Flop
reg [DATA_WIDTH-1:0] capture_ff;

always @ (posedge src_clk or negedge rst) begin
	if (!rst) capture_ff <= 0;	
	else capture_ff <= (~busy && send) ? data_src : capture_ff;
end

// Source Flip Flop
always @ (posedge src_clk or negedge rst) begin
	if (!rst) des_ff_in <= 0;
	else des_ff_in <= (src_ff_en) ? capture_ff : des_ff_in;
end

// Destination Flip Flop
always @ (posedge des_clk or negedge rst) begin
	if (!rst) data_des <= 0;
	else data_des <= (des_ff_en) ? des_ff_in : data_des;
end

endmodule

tb_handshake_synchronizer.v
`timescale 1ns/1ps

module handshake_synchronizer_tb();

localparam DATA_WIDTH = 8;

reg src_clk, des_clk, rst, send;
reg [DATA_WIDTH-1:0] data_src;
wire [DATA_WIDTH-1:0] data_des;
wire busy;

handshake_synchronizer #(.DATA_WIDTH(DATA_WIDTH)) dut (
	.src_clk(src_clk), .des_clk(des_clk), .rst(rst), .send(send),
	.data_src(data_src), .data_des(data_des), .busy(busy)
);

initial {src_clk, des_clk, rst, send} = 4'b0000;

always #20 src_clk = ~src_clk;
always #10 des_clk = ~des_clk;

initial begin
	data_src = 8'b0;
	forever @(negedge src_clk) data_src++;
end

initial begin
	$dumpfile("wav_handshake_synchronizer.vcd");
	$dumpvars(0,handshake_synchronizer_tb);

	#20 rst = 1'b1;
	#20 send = 1;
	#1000 $finish;
end

endmodule

wav_handshake_synchronizer.vcd
$date
	Sat Jun 27 09:59:01 2026
$end
$version
	Icarus Verilog
$end
$timescale
	1ps
$end
$scope module handshake_synchronizer_tb $end
$var wire 8 ! data_des [7:0] $end
$var wire 1 " busy $end
$var parameter 32 # DATA_WIDTH $end
$var reg 8 $ data_src [7:0] $end
$var reg 1 % des_clk $end
$var reg 1 & rst $end
$var reg 1 ' send $end
$var reg 1 ( src_clk $end
$scope module dut $end
$var wire 8 ) data_src [7:0] $end
$var wire 1 % des_clk $end
$var wire 1 & rst $end
$var wire 1 ' send $end
$var wire 1 ( src_clk $end
$var wire 1 * src_ff_en $end
$var wire 1 + req_src $end
$var wire 1 , req_des $end
$var wire 1 - des_ff_en $end
$var wire 1 " busy $end
$var wire 1 . ack_src $end
$var wire 1 / ack_des $end
$var parameter 32 0 DATA_WIDTH $end
$var reg 8 1 capture_ff [7:0] $end
$var reg 8 2 data_des [7:0] $end
$var reg 8 3 des_ff_in [7:0] $end
$scope module des_to_src $end
$var wire 1 ( clk $end
$var wire 1 & rst $end
$var wire 1 / in $end
$var reg 1 . out $end
$var reg 1 4 sync_ff $end
$upscope $end
$scope module destination_domain $end
$var wire 1 % des_clk $end
$var wire 1 & rst $end
$var wire 1 , req $end
$var parameter 2 5 idle $end
$var parameter 2 6 s1 $end
$var parameter 2 7 s2 $end
$var reg 1 / ack $end
$var reg 1 - des_ff_en $end
$var reg 2 8 next_state [1:0] $end
$var reg 2 9 present_state [1:0] $end
$upscope $end
$scope module sender_domain $end
$var wire 1 . ack $end
$var wire 1 & rst $end
$var wire 1 ' send $end
$var wire 1 ( src_clk $end
$var parameter 2 : idle $end
$var parameter 2 ; s1 $end
$var parameter 2 < s2 $end
$var parameter 2 = s3 $end
$var reg 1 " busy $end
$var reg 1 * load_src_reg_en $end
$var reg 2 > next_state [1:0] $end
$var reg 2 ? present_state [1:0] $end
$var reg 1 + req $end
$upscope $end
$scope module src_to_des $end
$var wire 1 % clk $end
$var wire 1 + in $end
$var wire 1 & rst $end
$var reg 1 , out $end
$var reg 1 @ sync_ff $end
$upscope $end
$upscope $end
$upscope $end
$enddefinitions $end
$comment Show the parameter values. $end
$dumpall
b11 =
b10 <
b1 ;
b0 :
b10 7
b1 6
b0 5
b1000 0
b1000 #
$end
#0
$dumpvars
0@
bx ?
b0 >
b0 9
b0 8
04
b0 3
b0 2
b0 1
0/
0.
0-
0,
0+
0*
b0 )
0(
0'
0&
0%
b0 $
0"
b0 !
$end
#10000
1%
#20000
b0 ?
0%
1&
1(
#30000
1%
#40000
b1 >
b1 $
b1 )
0%
1'
0(
#50000
1%
#60000
b10 >
1+
1"
1*
b1 ?
b1 1
0%
1(
#70000
1@
1%
#80000
b10 $
b10 )
0%
0(
#90000
b1 8
1,
1%
#100000
0*
b1 3
b10 ?
0%
1(
#110000
1-
1/
b10 8
b1 9
1%
#120000
b11 $
b11 )
0%
0(
#130000
0-
b1 !
b1 2
b10 9
1%
#140000
14
0%
1(
#150000
1%
#160000
b100 $
b100 )
0%
0(
#170000
1%
#180000
b11 >
1.
0%
1(
#190000
1%
#200000
b101 $
b101 )
0%
0(
#210000
1%
#220000
0+
b11 ?
0%
1(
#230000
0@
1%
#240000
b110 $
b110 )
0%
0(
#250000
b0 8
0,
1%
#260000
0%
1(
#270000
0/
b0 9
1%
#280000
b111 $
b111 )
0%
0(
#290000
1%
#300000
04
0%
1(
#310000
1%
#320000
b1000 $
b1000 )
0%
0(
#330000
1%
#340000
b0 >
0.
0%
1(
#350000
1%
#360000
b1001 $
b1001 )
0%
0(
#370000
1%
#380000
b1 >
0"
b0 ?
0%
1(
#390000
1%
#400000
b1010 $
b1010 )
0%
0(
#410000
1%
#420000
b10 >
1+
1"
1*
b1010 1
b1 ?
0%
1(
#430000
1@
1%
#440000
b1011 $
b1011 )
0%
0(
#450000
b1 8
1,
1%
#460000
0*
b10 ?
b1010 3
0%
1(
#470000
1-
1/
b10 8
b1 9
1%
#480000
b1100 $
b1100 )
0%
0(
#490000
0-
b1010 !
b1010 2
b10 9
1%
#500000
14
0%
1(
#510000
1%
#520000
b1101 $
b1101 )
0%
0(
#530000
1%
#540000
b11 >
1.
0%
1(
#550000
1%
#560000
b1110 $
b1110 )
0%
0(
#570000
1%
#580000
0+
b11 ?
0%
1(
#590000
0@
1%
#600000
b1111 $
b1111 )
0%
0(
#610000
b0 8
0,
1%
#620000
0%
1(
#630000
0/
b0 9
1%
#640000
b10000 $
b10000 )
0%
0(
#650000
1%
#660000
04
0%
1(
#670000
1%
#680000
b10001 $
b10001 )
0%
0(
#690000
1%
#700000
b0 >
0.
0%
1(
#710000
1%
#720000
b10010 $
b10010 )
0%
0(
#730000
1%
#740000
b1 >
0"
b0 ?
0%
1(
#750000
1%
#760000
b10011 $
b10011 )
0%
0(
#770000
1%
#780000
b10 >
1+
1"
1*
b1 ?
b10011 1
0%
1(
#790000
1@
1%
#800000
b10100 $
b10100 )
0%
0(
#810000
b1 8
1,
1%
#820000
0*
b10011 3
b10 ?
0%
1(
#830000
1-
1/
b10 8
b1 9
1%
#840000
b10101 $
b10101 )
0%
0(
#850000
0-
b10011 !
b10011 2
b10 9
1%
#860000
14
0%
1(
#870000
1%
#880000
b10110 $
b10110 )
0%
0(
#890000
1%
#900000
b11 >
1.
0%
1(
#910000
1%
#920000
b10111 $
b10111 )
0%
0(
#930000
1%
#940000
0+
b11 ?
0%
1(
#950000
0@
1%
#960000
b11000 $
b11000 )
0%
0(
#970000
b0 8
0,
1%
#980000
0%
1(
#990000
0/
b0 9
1%
#1000000
b11001 $
b11001 )
0%
0(
#1010000
1%
#1020000
04
0%
1(
#1030000
1%
#1040000
b11010 $
b11010 )
0%
0(
